Workbook

Sheet MASTER ALLOCATION
A1: DNA ENTERTAINMENT — DEFINITIVE £10,000 ALLOCATION | 10 Positions + £1,000 Cash | March–June 2026
A2: ⚠️ Speculative analysis. Not financial advice. All investments carry risk including total loss. Consult a qualified advisor. Incorporating Gemini tactical overlay (trailing stops + tranche deployment).
A4: Tier | B4: Ticker | C4: Company | D4: £ Alloc | E4: Entry | F4: Ccy | G4: Hard Stop | H4: Trail Trigger (+30%) | I4: Crude / Asset Quality | J4: API° | K4: Brent Prem | L4: Hormuz Impact | M4: Squeeze Prob | N4: Catalyst 1 (Nearest) | O4: Prob | P4: Catalyst 2 | Q4: Prob | R4: Catalyst Status | S4: Key Risk | T4: Div/ Yield | U4: Action | V4: Deploy Tranche | W4: Deploy Day
A5: A | B5: AET | C5: Afentra | D5: 1000 | E5: 0.72 | F5: £ | G5: 0.58 | H5: 0.94 | I5: Light-Med Sweet Angola | J5: 28-32° | K5: -$2 to -$4 | L5: V.STRONG | M5: MED-HIGH | N5: Rule 2.7 bid May-Jun (Jefferies) | O5: 0.65 | P5: Etu acquisition + Block 3/05 spudding NOW | Q5: 0.8 | R5: LIVE — Jefferies process + rig secured | S5: Bid may not materialise | T5: N/A | U5: STRONG BUY | V5: 1.8 | W5: Tranche 1
A6: A | B6: IMPP | C6: Imperial Petroleum | D6: 1000 | E6: 4.1 | F6: $ | G6: 2.8 | H6: 5.33 | I6: Shipping — Rate Driven | J6: N/A | K6: N/A | L6: EXTREME | M6: HIGH | N6: Q1 earnings at peak Hormuz rates | O6: 0.9 | P6: Fleet 24→26 vessels + $10M buyback | Q6: 0.85 | R6: LIVE — Fleet utilisation maxed | S6: Dilutive offerings history | T6: $10M buyback | U6: STRONG BUY | V6: 20 | W6: Tranche 1
A7: A | B7: GKP | C7: Gulf Keystone | D7: 500 | E7: 2.04 | F7: £ | G7: 1.65 | H7: 2.65 | I7: Light Sweet CEYHAN PREM | J7: ~35° | K7: -$10 interim→$90+ intl | L7: EXTREME BINARY | M7: MED-HIGH | N7: RESTART CONFIRMED Mar 27 — exports via Ceyhan | O7: 0.95 | P7: Intl pricing + Dividend Apr 27 (12.4%) | Q7: 0.6 | R7: CONFIRMED — signing agreement with Iraq/KRG | S7: Iran conflict proximity (exports go NW to Turkey, NOT through Gulf) | T7: 12.4% | U7: BUY | V7: 4.5 | W7: Tranche 1
A8: A | B8: KOS | C8: Kosmos Energy | D8: 500 | E8: 2.4 | F8: $ | G8: 1.6 | H8: 3.12 | I8: Premium Light Sweet + LNG | J8: ~37° | K8: Flat to +$2 | L8: V.STRONG | M8: MED-HIGH | N8: GTA LNG cargoes ramp NOW (32-36 yr target) | O8: 0.85 | P8: Jubilee optimisation + analyst upgrades | Q8: 0.7 | R8: LIVE — cargoes delivering into crisis | S8: Debt leverage ($2.5B) | T8: N/A | U8: BUY | V8: 10 | W8: Tranche 1
A9: A | B9: FRO | C9: Frontline | D9: 500 | E9: 33.78 | F9: $ | G9: 25 | H9: 43.91 | I9: Shipping — 81 VLCCs | J9: N/A | K9: N/A | L9: EXTREME | M9: MED-HIGH | N9: Q1 earnings $107k/day VLCC (May report) | O9: 0.9 | P9: Newbuilding deliveries + fleet renewal | Q9: 0.8 | R9: LIVE — rates already captured | S9: Cyclical rate collapse on ceasefire | T9: ~12% variable | U9: BUY | V9: 70 | W9: Tranche 1
A10: B | B10: JSE | C10: Jadestone Energy | D10: 500 | E10: 0.28 | F10: £ | G10: 0.2 | H10: 0.364 | I10: Condensate ASIA PREMIUM | J10: 38-47° | K10: +$3 to +$10 condensate | L10: STRONG | M10: MED-HIGH | N10: Vietnam FDP CONFIRMED Mar 18 (32 MMboe booked) | O10: 1 | P10: PM323 Malaysia infill drilling Q2 | Q10: 0.7 | R10: CONFIRMED — reserves booked, farm-in launching | S10: Cyclone Narelle Stag damage (monitor RNS) | T10: N/A | U10: STRONG BUY | V10: 0.75 | W10: Tranche 2
A11: B | B11: ENQ | C11: EnQuest | D11: 500 | E11: 0.13 | F11: £ | G11: 0.09 | H11: 0.169 | I11: Med Sour + ASIA PREMIUM | J11: 30-40° | K11: Brent + Asia prem | L11: STRONG | M11: MED-HIGH | N11: Magnus 6-well infill drilling commencing Q2 | O11: 0.85 | P11: Seligi gas 100mmscf/d + Serica merger talks (Mar 7) | Q11: 0.6 | R11: CONFIRMED — March prod >50,000 boepd | S11: UK windfall tax 78% (EPL) | T11: ~5% + maiden div Jun 2026 | U11: BUY | V11: 0.38 | W11: Tranche 2
A12: B | B12: RKH | C12: Rockhopper | D12: 500 | E12: 0.75 | F12: £ | G12: 0.55 | H12: 0.975 | I12: Light Sweet Atlantic | J12: ~32° | K12: -$1 to flat | L12: V.STRONG | M12: MED-HIGH | N12: Sea Lion Phase 1 engineering (FID'd Dec 2025) | O12: 0.85 | P12: Navitas milestones + FPSO + Aberdeen office | Q12: 0.7 | R12: ON TRACK — $2.1B project advancing | S12: Argentina geo risk (reduced under Milei) | T12: N/A | U12: HOLD | V12: 1.8 | W12: Tranche 2
A13: C | B13: PXEN | C13: Prospex Energy | D13: 750 | E13: 0.0485 | F13: £ | G13: 0.03 | H13: 0.063 | I13: EU Gas — TTF Premium | J13: Gas | K13: TTF benchmark (~€52/MWh) | L13: V.STRONG | M13: MED-HIGH | N13: El Romeral permits (EIA cleared, 0 objections) | O13: 0.58 | P13: El Romeral plant restarted + Polish licences | Q13: 0.5 | R13: PROGRESSING — MITECO 90-180 day review | S13: Spanish permitting delays | T13: N/A | U13: SPEC BUY | V13: 0.25 | W13: Tranche 2
A14: C | B14: BOR | C14: Borders & Southern | D14: 750 | E14: 0.1 | F14: £ | G14: 0.05 | H14: 0.13 | I14: ULTRA-LIGHT CONDENSATE | J14: 46-49° | K14: +$5-10 condensate | L14: V.STRONG | M14: MED-HIGH | N14: Farm-out discussions (Sea Lion FID de-risks Falklands) | O14: 0.35 | P14: Licence deadline Dec 2026 creates urgency | Q14: 0.7 | R14: ACTIVE — 'encouraged by industry interest' | S14: Cash runway to mid-2026 only | T14: N/A | U14: SPEC BUY | V14: 1 | W14: Tranche 2
B15: HBR | C15: Harbour Energy | D15: 1000 | E15: 300p | G15: 240p | H15: 650p | N15: European Gas Savior: Selling Johan Sverdrup at record premiums + critical UK/Norway domestic gas as Qatar LNG strands. | T15: ~7.7% | U15: DIV BUY
B16: PTAL | C16: PetroTal | D16: 500 | E16: 38p | G16: 30p | H16: 110p | N16: Geopolitical Safe-Haven: Peruvian oil entirely isolated from the Middle East. Ramping up to 20,000+ bopd. | T16: ~8.4% | U16: DIV BUY
B17: SEPL | C17: Seplat Energy | D17: 500 | E17: 456p | G17: 350p | H17: 900p | N17: Premium West African: Bonny Light crude replaces Gulf oil. ANOH gas plant ramping up right as EU needs non-Russian/Qatar gas. | T17: ~7.0% | U17: DIV BUY
B18: PBR | C18: Petrobras ADR | D18: 500 | E18: $14.50 | G18: $11.00 | H18: $30.00 | N18: Atlantic Deepwater Giant: Prints cash at $100+ Brent. Massive special dividends expected as state demands payouts. | T18: 10.0%+ | U18: DIV BUY
A19: — | B19: CASH | C19: Dry Powder Reserve | D19: 1000 | R19: Deploy on: AET bid (£300) / GKP intl pricing (£300) / Hormuz extends (£400 to IMPP+FRO) / BOR partner (all remaining)
A20: DEPLOYMENT STRATEGY (Gemini tactical overlay adopted):
A21: → Tranche 1 (Apr 1): Deploy £7,000 into AET, IMPP, GKP, KOS, FRO — these are the immediate macro beneficiaries with confirmed catalysts firing NOW.
A22: → Tranche 2 (Apr 2-3): Deploy £2,000 into JSE (after Stag update RNS), ENQ, RKH — confirmed Q2 catalysts. Deploy £1,500 into PXEN + BOR — speculative asymmetric.
A23: → Cash Reserve (£1,000): Hold for reactive deployment on confirmed catalyst announcements (RNS alerts via Investegate.co.uk).
A24: → STOP-LOSS PROTOCOL: Set HARD stops immediately on fill. When any position hits +30% (Trail Trigger column), convert to 15% TRAILING STOP to lock in profits.
A25: → EXIT WINDOW: Systematic profit-taking by late June 2026. Ukraine precedent = ~4 months elevated. EIA forecasts oil <$80 in Q3. Do not hold through the peak.

Sheet BEAR CASE
A1: DNA ENTERTAINMENT — BEAR CASE
A2: Ceasefire announced. Oil crashes to $60-70. Squeeze evaporates. Stop-losses protect capital.
A3: Scenario Probability: ~35-40%
A5: Tier | B5: Ticker | C5: Company | D5: £ Invested | E5: Entry Price | F5: Target Price | G5: Shares (approx) | H5: £ Return | I5: Profit £ | J5: Return % | K5: Crude Quality Edge | L5: Catalyst Outcome | M5: Div Income Est
A6: A | B6: AET | C6: Afentra | D6: 1500 | E6: 0.72 | F6: 0.58 | G6: =D6/E6 -> 2083.3333 | H6: =G6*F6 -> 1208.3333 | I6: =H6-D6 -> -291.66667 | J6: =I6/D6 -> -0.19444444 | K6: Light-Med Sweet Angola | L6: Stop at 58p. Bid process may still protect. | M6: ~£0
A7: A | B7: IMPP | C7: Imperial Petroleum | D7: 1500 | E7: 4.1 | F7: 2.8 | G7: =D7/E7 -> 365.85366 | H7: =G7*F7 -> 1024.3902 | I7: =H7-D7 -> -475.60976 | J7: =I7/D7 -> -0.31707317 | K7: Shipping — Rate Driven | L7: Stop at $2.80. Fleet value floor. | M7: ~£0
A8: A | B8: GKP | C8: Gulf Keystone | D8: 1000 | E8: 2.04 | F8: 1.65 | G8: =D8/E8 -> 490.19608 | H8: =G8*F8 -> 808.82353 | I8: =H8-D8 -> -191.17647 | J8: =I8/D8 -> -0.19117647 | K8: Light Sweet CEYHAN PREM | L8: Stop at 165p. Shut-in extends. | M8: ~£25
A9: A | B9: KOS | C9: Kosmos Energy | D9: 1000 | E9: 2.4 | F9: 1.6 | G9: =D9/E9 -> 416.66667 | H9: =G9*F9 -> 666.66667 | I9: =H9-D9 -> -333.33333 | J9: =I9/D9 -> -0.33333333 | K9: Premium Light Sweet + LNG | L9: Stop at $1.60. Debt weighs. | M9: ~£0
A10: A | B10: FRO | C10: Frontline | D10: 500 | E10: 33.78 | F10: 25 | G10: =D10/E10 -> 14.801658 | H10: =G10*F10 -> 370.04144 | I10: =H10-D10 -> -129.95856 | J10: =I10/D10 -> -0.25991711 | K10: Shipping — 81 VLCCs | L10: Stop at $25. Rates collapse. | M10: ~£15
A11: B | B11: JSE | C11: Jadestone Energy | D11: 1000 | E11: 0.28 | F11: 0.2 | G11: =D11/E11 -> 3571.4286 | H11: =G11*F11 -> 714.28571 | I11: =H11-D11 -> -285.71429 | J11: =I11/D11 -> -0.28571429 | K11: Condensate ASIA PREMIUM | L11: Stop at 20p. FDP provides some floor. | M11: ~£0
A12: B | B12: ENQ | C12: EnQuest | D12: 500 | E12: 0.13 | F12: 0.09 | G12: =D12/E12 -> 3846.1538 | H12: =G12*F12 -> 346.15385 | I12: =H12-D12 -> -153.84615 | J12: =I12/D12 -> -0.30769231 | K12: Med Sour + ASIA PREMIUM | L12: Stop at 9p. Tax + low oil. | M12: ~£4
A13: B | B13: RKH | C13: Rockhopper | D13: 500 | E13: 0.75 | F13: 0.55 | G13: =D13/E13 -> 666.66667 | H13: =G13*F13 -> 366.66667 | I13: =H13-D13 -> -133.33333 | J13: =I13/D13 -> -0.26666667 | K13: Light Sweet Atlantic | L13: Stop at 55p. Delays. | M13: ~£0
A14: C | B14: PXEN | C14: Prospex Energy | D14: 750 | E14: 0.0485 | F14: 0.03 | G14: =D14/E14 -> 15463.918 | H14: =G14*F14 -> 463.91753 | I14: =H14-D14 -> -286.08247 | J14: =I14/D14 -> -0.3814433 | K14: EU Gas — TTF Premium | L14: Stop at 3p. Permits delayed. | M14: ~£0
A15: C | B15: BOR | C15: Borders & Southern | D15: 750 | E15: 0.1 | F15: 0.05 | G15: =D15/E15 -> 7500 | H15: =G15*F15 -> 375 | I15: =H15-D15 -> -375 | J15: =I15/D15 -> -0.5 | K15: ULTRA-LIGHT CONDENSATE | L15: Stop at 5p. No partner. | M15: ~£0
A16: — | B16: CASH | C16: Reserve | D16: 1000 | H16: 1000 | I16: 0
B17: PORTFOLIO TOTAL | D17: =SUM(D6:D16) -> 10000 | H17: =SUM(H6:H16) -> 7344.279 | I17: =H17-D17 -> -2655.721 | J17: =I17/D17 -> -0.2655721
A19: BEAR CASE — Ceasefire announced. Oil crashes to $60-70. Squeeze evaporates. Stop-losses protect capital.
A20: Invested: | C20: =D17 -> 10000
A21: Value: | C21: =H17 -> 7344.279
A22: Profit: | C22: =I17 -> -2655.721
A23: Return: | C23: =J17 -> -0.2655721

Sheet BASE CASE
A1: DNA ENTERTAINMENT — BASE CASE
A2: Hormuz resolves Q3. Oil $75-85. Most company catalysts fire on fundamentals. Dividends collected.
A3: Scenario Probability: ~45-50%
A5: Tier | B5: Ticker | C5: Company | D5: £ Invested | E5: Entry Price | F5: Target Price | G5: Shares (approx) | H5: £ Return | I5: Profit £ | J5: Return % | K5: Crude Quality Edge | L5: Catalyst Outcome | M5: Div Income Est
A6: A | B6: AET | C6: Afentra | D6: 1500 | E6: 0.72 | F6: 0.85 | G6: =D6/E6 -> 2083.3333 | H6: =G6*F6 -> 1770.8333 | I6: =H6-D6 -> 270.83333 | J6: =I6/D6 -> 0.18055556 | K6: Light-Med Sweet Angola | L6: Bid at modest premium. Steady. | M6: ~£0
A7: A | B7: IMPP | C7: Imperial Petroleum | D7: 1500 | E7: 4.1 | F7: 8 | G7: =D7/E7 -> 365.85366 | H7: =G7*F7 -> 2926.8293 | I7: =H7-D7 -> 1426.8293 | J7: =I7/D7 -> 0.95121951 | K7: Shipping — Rate Driven | L7: Re-rates to book value. Fleet earning. | M7: ~£0
A8: A | B8: GKP | C8: Gulf Keystone | D8: 1000 | E8: 2.04 | F8: 2.8 | G8: =D8/E8 -> 490.19608 | H8: =G8*F8 -> 1372.549 | I8: =H8-D8 -> 372.54902 | J8: =I8/D8 -> 0.37254902 | K8: Light Sweet CEYHAN PREM | L8: Intl pricing partially achieved + dividend. | M8: ~£25
A9: A | B9: KOS | C9: Kosmos Energy | D9: 1000 | E9: 2.4 | F9: 4.5 | G9: =D9/E9 -> 416.66667 | H9: =G9*F9 -> 1875 | I9: =H9-D9 -> 875 | J9: =I9/D9 -> 0.875 | K9: Premium Light Sweet + LNG | L9: GTA LNG delivers at $75 oil. | M9: ~£0
A10: A | B10: FRO | C10: Frontline | D10: 500 | E10: 33.78 | F10: 40 | G10: =D10/E10 -> 14.801658 | H10: =G10*F10 -> 592.06631 | I10: =H10-D10 -> 92.066311 | J10: =I10/D10 -> 0.18413262 | K10: Shipping — 81 VLCCs | L10: Rates normalise but profitable. | M10: ~£15
A11: B | B11: JSE | C11: Jadestone Energy | D11: 1000 | E11: 0.28 | F11: 0.4 | G11: =D11/E11 -> 3571.4286 | H11: =G11*F11 -> 1428.5714 | I11: =H11-D11 -> 428.57143 | J11: =I11/D11 -> 0.42857143 | K11: Condensate ASIA PREMIUM | L11: FDP booked. PM323 wells online. | M11: ~£0
A12: B | B12: ENQ | C12: EnQuest | D12: 500 | E12: 0.13 | F12: 0.18 | G12: =D12/E12 -> 3846.1538 | H12: =G12*F12 -> 692.30769 | I12: =H12-D12 -> 192.30769 | J12: =I12/D12 -> 0.38461538 | K12: Med Sour + ASIA PREMIUM | L12: Magnus drilling adds production. | M12: ~£4
A13: B | B13: RKH | C13: Rockhopper | D13: 500 | E13: 0.75 | F13: 0.95 | G13: =D13/E13 -> 666.66667 | H13: =G13*F13 -> 633.33333 | I13: =H13-D13 -> 133.33333 | J13: =I13/D13 -> 0.26666667 | K13: Light Sweet Atlantic | L13: Milestones met on schedule. | M13: ~£0
A14: C | B14: PXEN | C14: Prospex Energy | D14: 750 | E14: 0.0485 | F14: 0.08 | G14: =D14/E14 -> 15463.918 | H14: =G14*F14 -> 1237.1134 | I14: =H14-D14 -> 487.1134 | J14: =I14/D14 -> 0.64948454 | K14: EU Gas — TTF Premium | L14: Permits progressing. Some production. | M14: ~£0
A15: C | B15: BOR | C15: Borders & Southern | D15: 750 | E15: 0.1 | F15: 0.18 | G15: =D15/E15 -> 7500 | H15: =G15*F15 -> 1350 | I15: =H15-D15 -> 600 | J15: =I15/D15 -> 0.8 | K15: ULTRA-LIGHT CONDENSATE | L15: Farm-out talks continue. | M15: ~£0
A16: — | B16: CASH | C16: Reserve | D16: 1000 | H16: 1000 | I16: 0
B17: PORTFOLIO TOTAL | D17: =SUM(D6:D16) -> 10000 | H17: =SUM(H6:H16) -> 14878.604 | I17: =H17-D17 -> 4878.6038 | J17: =I17/D17 -> 0.48786038
A19: BASE CASE — Hormuz resolves Q3. Oil $75-85. Most company catalysts fire on fundamentals. Dividends collected.
A20: Invested: | C20: =D17 -> 10000
A21: Value: | C21: =H17 -> 14878.604
A22: Profit: | C22: =I17 -> 4878.6038
A23: Return: | C23: =J17 -> 0.48786038

Sheet REALISTIC MOONSHOT
A1: DNA ENTERTAINMENT — REALISTIC MOONSHOT
A2: Oil $110-120 sustained. Most catalysts fire. Moderate re-ratings. 3 independent engines running.
A3: Scenario Probability: ~25-30%
A5: Tier | B5: Ticker | C5: Company | D5: £ Invested | E5: Entry Price | F5: Target Price | G5: Shares (approx) | H5: £ Return | I5: Profit £ | J5: Return % | K5: Crude Quality Edge | L5: Catalyst Outcome | M5: Div Income Est
A6: A | B6: AET | C6: Afentra | D6: 1500 | E6: 0.72 | F6: 1 | G6: =D6/E6 -> 2083.3333 | H6: =G6*F6 -> 2083.3333 | I6: =H6-D6 -> 583.33333 | J6: =I6/D6 -> 0.38888889 | K6: Light-Med Sweet Angola | L6: Bid 100p in $110 oil. | M6: ~£0
A7: A | B7: IMPP | C7: Imperial Petroleum | D7: 1500 | E7: 4.1 | F7: 8 | G7: =D7/E7 -> 365.85366 | H7: =G7*F7 -> 2926.8293 | I7: =H7-D7 -> 1426.8293 | J7: =I7/D7 -> 0.95121951 | K7: Shipping — Rate Driven | L7: Fleet 26 vessels. Q1 earnings explosive. | M7: ~£0
A8: A | B8: GKP | C8: Gulf Keystone | D8: 1000 | E8: 2.04 | F8: 3 | G8: =D8/E8 -> 490.19608 | H8: =G8*F8 -> 1470.5882 | I8: =H8-D8 -> 470.58824 | J8: =I8/D8 -> 0.47058824 | K8: Light Sweet CEYHAN PREM | L8: Full restart + $90+ intl pricing. | M8: ~£25
A9: A | B9: KOS | C9: Kosmos Energy | D9: 1000 | E9: 2.4 | F9: 5 | G9: =D9/E9 -> 416.66667 | H9: =G9*F9 -> 2083.3333 | I9: =H9-D9 -> 1083.3333 | J9: =I9/D9 -> 1.0833333 | K9: Premium Light Sweet + LNG | L9: GTA + Jubilee at $110. FCF inflection. | M9: ~£0
A10: A | B10: FRO | C10: Frontline | D10: 500 | E10: 33.78 | F10: 42 | G10: =D10/E10 -> 14.801658 | H10: =G10*F10 -> 621.66963 | I10: =H10-D10 -> 121.66963 | J10: =I10/D10 -> 0.24333925 | K10: Shipping — 81 VLCCs | L10: VLCC $100k+/day sustained. | M10: ~£15
A11: B | B11: JSE | C11: Jadestone Energy | D11: 1000 | E11: 0.28 | F11: 0.45 | G11: =D11/E11 -> 3571.4286 | H11: =G11*F11 -> 1607.1429 | I11: =H11-D11 -> 607.14286 | J11: =I11/D11 -> 0.60714286 | K11: Condensate ASIA PREMIUM | L11: FDP + PM323 + $10 condensate prem. | M11: ~£0
A12: B | B12: ENQ | C12: EnQuest | D12: 500 | E12: 0.13 | F12: 0.22 | G12: =D12/E12 -> 3846.1538 | H12: =G12*F12 -> 846.15385 | I12: =H12-D12 -> 346.15385 | J12: =I12/D12 -> 0.69230769 | K12: Med Sour + ASIA PREMIUM | L12: Magnus + Seligi + Sverdrup-type prem. | M12: ~£4
A13: B | B13: RKH | C13: Rockhopper | D13: 500 | E13: 0.75 | F13: 1 | G13: =D13/E13 -> 666.66667 | H13: =G13*F13 -> 666.66667 | I13: =H13-D13 -> 166.66667 | J13: =I13/D13 -> 0.33333333 | K13: Light Sweet Atlantic | L13: Sea Lion advancing at $110+ oil. | M13: ~£0
A14: C | B14: PXEN | C14: Prospex Energy | D14: 750 | E14: 0.0485 | F14: 0.1 | G14: =D14/E14 -> 15463.918 | H14: =G14*F14 -> 1546.3918 | I14: =H14-D14 -> 796.39175 | J14: =I14/D14 -> 1.0618557 | K14: EU Gas — TTF Premium | L14: Permits granted. 2 wells producing. TTF €50+. | M14: ~£0
A15: C | B15: BOR | C15: Borders & Southern | D15: 750 | E15: 0.1 | F15: 0.25 | G15: =D15/E15 -> 7500 | H15: =G15*F15 -> 1875 | I15: =H15-D15 -> 1125 | J15: =I15/D15 -> 1.5 | K15: ULTRA-LIGHT CONDENSATE | L15: Farm-out interest from Sea Lion de-risk. | M15: ~£0
A16: — | B16: CASH | C16: Reserve | D16: 1000 | H16: 1000 | I16: 0
B17: PORTFOLIO TOTAL | D17: =SUM(D6:D16) -> 10000 | H17: =SUM(H6:H16) -> 16727.109 | I17: =H17-D17 -> 6727.1089 | J17: =I17/D17 -> 0.67271089
A19: REALISTIC MOONSHOT — Oil $110-120 sustained. Most catalysts fire. Moderate re-ratings. 3 independent engines running.
A20: Invested: | C20: =D17 -> 10000
A21: Value: | C21: =H17 -> 16727.109
A22: Profit: | C22: =I17 -> 6727.1089
A23: Return: | C23: =J17 -> 0.67271089

Sheet OPTIMISTIC MOONSHOT
A1: DNA ENTERTAINMENT — OPTIMISTIC MOONSHOT
A2: Oil $120-130 sustained. All catalysts fire. Squeezes materialise. Crude premiums widen.
A3: Scenario Probability: ~10-15%
A5: Tier | B5: Ticker | C5: Company | D5: £ Invested | E5: Entry Price | F5: Target Price | G5: Shares (approx) | H5: £ Return | I5: Profit £ | J5: Return % | K5: Crude Quality Edge | L5: Catalyst Outcome | M5: Div Income Est
A6: A | B6: AET | C6: Afentra | D6: 1500 | E6: 0.72 | F6: 1.2 | G6: =D6/E6 -> 2083.3333 | H6: =G6*F6 -> 2500 | I6: =H6-D6 -> 1000 | J6: =I6/D6 -> 0.66666667 | K6: Light-Med Sweet Angola | L6: Competitive bid 120p. Multiple bidders. | M6: ~£0
A7: A | B7: IMPP | C7: Imperial Petroleum | D7: 1500 | E7: 4.1 | F7: 12 | G7: =D7/E7 -> 365.85366 | H7: =G7*F7 -> 4390.2439 | I7: =H7-D7 -> 2890.2439 | J7: =I7/D7 -> 1.9268293 | K7: Shipping — Rate Driven | L7: NAV re-rating begins. Buyback reduces float. | M7: ~£0
A8: A | B8: GKP | C8: Gulf Keystone | D8: 1000 | E8: 2.04 | F8: 3.6 | G8: =D8/E8 -> 490.19608 | H8: =G8*F8 -> 1764.7059 | I8: =H8-D8 -> 764.70588 | J8: =I8/D8 -> 0.76470588 | K8: Light Sweet CEYHAN PREM | L8: Intl pricing at $120+. Ceyhan premium. | M8: ~£25
A9: A | B9: KOS | C9: Kosmos Energy | D9: 1000 | E9: 2.4 | F9: 7 | G9: =D9/E9 -> 416.66667 | H9: =G9*F9 -> 2916.6667 | I9: =H9-D9 -> 1916.6667 | J9: =I9/D9 -> 1.9166667 | K9: Premium Light Sweet + LNG | L9: GTA LNG at $25/MMBtu spot. KOS $7+. | M9: ~£0
A10: A | B10: FRO | C10: Frontline | D10: 500 | E10: 33.78 | F10: 50 | G10: =D10/E10 -> 14.801658 | H10: =G10*F10 -> 740.08289 | I10: =H10-D10 -> 240.08289 | J10: =I10/D10 -> 0.48016578 | K10: Shipping — 81 VLCCs | L10: VLCC $120k/day. Newbuildings online. | M10: ~£15
A11: B | B11: JSE | C11: Jadestone Energy | D11: 1000 | E11: 0.28 | F11: 0.54 | G11: =D11/E11 -> 3571.4286 | H11: =G11*F11 -> 1928.5714 | I11: =H11-D11 -> 928.57143 | J11: =I11/D11 -> 0.92857143 | K11: Condensate ASIA PREMIUM | L11: All catalysts + 47° condensate $15 prem. | M11: ~£0
A12: B | B12: ENQ | C12: EnQuest | D12: 500 | E12: 0.13 | F12: 0.28 | G12: =D12/E12 -> 3846.1538 | H12: =G12*F12 -> 1076.9231 | I12: =H12-D12 -> 576.92308 | J12: =I12/D12 -> 1.1538462 | K12: Med Sour + ASIA PREMIUM | L12: Magnus peak + Serica merger re-rates. | M12: ~£4
A13: B | B13: RKH | C13: Rockhopper | D13: 500 | E13: 0.75 | F13: 1.2 | G13: =D13/E13 -> 666.66667 | H13: =G13*F13 -> 800 | I13: =H13-D13 -> 300 | J13: =I13/D13 -> 0.6 | K13: Light Sweet Atlantic | L13: Falklands premium. Oil $120+. | M13: ~£0
A14: C | B14: PXEN | C14: Prospex Energy | D14: 750 | E14: 0.0485 | F14: 0.15 | G14: =D14/E14 -> 15463.918 | H14: =G14*F14 -> 2319.5876 | I14: =H14-D14 -> 1569.5876 | J14: =I14/D14 -> 2.0927835 | K14: EU Gas — TTF Premium | L14: Full permits + 5 wells. TTF €55+. | M14: ~£0
A15: C | B15: BOR | C15: Borders & Southern | D15: 750 | E15: 0.1 | F15: 0.5 | G15: =D15/E15 -> 7500 | H15: =G15*F15 -> 3750 | I15: =H15-D15 -> 3000 | J15: =I15/D15 -> 4 | K15: ULTRA-LIGHT CONDENSATE | L15: Partner identified. Term sheet signed. | M15: ~£0
A16: — | B16: CASH | C16: Reserve | D16: 1000 | H16: 1000 | I16: 0
B17: PORTFOLIO TOTAL | D17: =SUM(D6:D16) -> 10000 | H17: =SUM(H6:H16) -> 23186.781 | I17: =H17-D17 -> 13186.781 | J17: =I17/D17 -> 1.3186781
A19: OPTIMISTIC MOONSHOT — Oil $120-130 sustained. All catalysts fire. Squeezes materialise. Crude premiums widen.
A20: Invested: | C20: =D17 -> 10000
A21: Value: | C21: =H17 -> 23186.781
A22: Profit: | C22: =I17 -> 13186.781
A23: Return: | C23: =J17 -> 1.3186781

Sheet EVERYTHING HITS
A1: DNA ENTERTAINMENT — EVERYTHING HITS
A2: Oil $130+ sustained. Squeezes accelerate. Premium crude differentials at historic wides. Every engine firing.
A3: Scenario Probability: ~5-8%
A5: Tier | B5: Ticker | C5: Company | D5: £ Invested | E5: Entry Price | F5: Target Price | G5: Shares (approx) | H5: £ Return | I5: Profit £ | J5: Return % | K5: Crude Quality Edge | L5: Catalyst Outcome | M5: Div Income Est
A6: A | B6: AET | C6: Afentra | D6: 1500 | E6: 0.72 | F6: 1.5 | G6: =D6/E6 -> 2083.3333 | H6: =G6*F6 -> 3125 | I6: =H6-D6 -> 1625 | J6: =I6/D6 -> 1.0833333 | K6: Light-Med Sweet Angola | L6: Premium bid 150p. Takeover war. | M6: ~£0
A7: A | B7: IMPP | C7: Imperial Petroleum | D7: 1500 | E7: 4.1 | F7: 16 | G7: =D7/E7 -> 365.85366 | H7: =G7*F7 -> 5853.6585 | I7: =H7-D7 -> 4353.6585 | J7: =I7/D7 -> 2.902439 | K7: Shipping — Rate Driven | L7: Squeeze towards NAV $11.38. | M7: ~£0
A8: A | B8: GKP | C8: Gulf Keystone | D8: 1000 | E8: 2.04 | F8: 4.2 | G8: =D8/E8 -> 490.19608 | H8: =G8*F8 -> 2058.8235 | I8: =H8-D8 -> 1058.8235 | J8: =I8/D8 -> 1.0588235 | K8: Light Sweet CEYHAN PREM | L8: Intl pricing at $130. Ceyhan monopoly. | M8: ~£25
A9: A | B9: KOS | C9: Kosmos Energy | D9: 1000 | E9: 2.4 | F9: 8.5 | G9: =D9/E9 -> 416.66667 | H9: =G9*F9 -> 3541.6667 | I9: =H9-D9 -> 2541.6667 | J9: =I9/D9 -> 2.5416667 | K9: Premium Light Sweet + LNG | L9: DCF $6.87 achieved. Dual peak. | M9: ~£0
A10: A | B10: FRO | C10: Frontline | D10: 500 | E10: 33.78 | F10: 60 | G10: =D10/E10 -> 14.801658 | H10: =G10*F10 -> 888.09947 | I10: =H10-D10 -> 388.09947 | J10: =I10/D10 -> 0.77619893 | K10: Shipping — 81 VLCCs | L10: VLCC $150k/day. $2+/share divs. | M10: ~£15
A11: B | B11: JSE | C11: Jadestone Energy | D11: 1000 | E11: 0.28 | F11: 0.65 | G11: =D11/E11 -> 3571.4286 | H11: =G11*F11 -> 2321.4286 | I11: =H11-D11 -> 1321.4286 | J11: =I11/D11 -> 1.3214286 | K11: Condensate ASIA PREMIUM | L11: Condensate $15+ prem. Vietnam + Malaysia. | M11: ~£0
A12: B | B12: ENQ | C12: EnQuest | D12: 500 | E12: 0.13 | F12: 0.33 | G12: =D12/E12 -> 3846.1538 | H12: =G12*F12 -> 1269.2308 | I12: =H12-D12 -> 769.23077 | J12: =I12/D12 -> 1.5384615 | K12: Med Sour + ASIA PREMIUM | L12: Combined entity re-rates. Peak prem. | M12: ~£4
A13: B | B13: RKH | C13: Rockhopper | D13: 500 | E13: 0.75 | F13: 1.5 | G13: =D13/E13 -> 666.66667 | H13: =G13*F13 -> 1000 | I13: =H13-D13 -> 500 | J13: =I13/D13 -> 1 | K13: Light Sweet Atlantic | L13: Falklands = new frontier valued. | M13: ~£0
A14: C | B14: PXEN | C14: Prospex Energy | D14: 750 | E14: 0.0485 | F14: 0.2 | G14: =D14/E14 -> 15463.918 | H14: =G14*F14 -> 3092.7835 | I14: =H14-D14 -> 2342.7835 | J14: =I14/D14 -> 3.1237113 | K14: EU Gas — TTF Premium | L14: 5 wells + all assets. TTF €60+. | M14: ~£0
A15: C | B15: BOR | C15: Borders & Southern | D15: 750 | E15: 0.1 | F15: 0.8 | G15: =D15/E15 -> 7500 | H15: =G15*F15 -> 6000 | I15: =H15-D15 -> 5250 | J15: =I15/D15 -> 7 | K15: ULTRA-LIGHT CONDENSATE | L15: Partner announced. Farm-in terms agreed. | M15: ~£0
A16: — | B16: CASH | C16: Reserve | D16: 1000 | H16: 1000 | I16: 0
B17: PORTFOLIO TOTAL | D17: =SUM(D6:D16) -> 10000 | H17: =SUM(H6:H16) -> 30150.691 | I17: =H17-D17 -> 20150.691 | J17: =I17/D17 -> 2.0150691
A19: EVERYTHING HITS — Oil $130+ sustained. Squeezes accelerate. Premium crude differentials at historic wides. Every engine firing.
A20: Invested: | C20: =D17 -> 10000
A21: Value: | C21: =H17 -> 30150.691
A22: Profit: | C22: =I17 -> 20150.691
A23: Return: | C23: =J17 -> 2.0150691

Sheet ABSOLUTE CEILING
A1: DNA ENTERTAINMENT — ABSOLUTE CEILING
A2: Oil $140-150. IMPP squeezes past NAV. BOR partner. PXEN full permits. Prolonged Hormuz. Historic energy crisis.
A3: Scenario Probability: ~2-5%
A5: Tier | B5: Ticker | C5: Company | D5: £ Invested | E5: Entry Price | F5: Target Price | G5: Shares (approx) | H5: £ Return | I5: Profit £ | J5: Return % | K5: Crude Quality Edge | L5: Catalyst Outcome | M5: Div Income Est
A6: A | B6: AET | C6: Afentra | D6: 1500 | E6: 0.72 | F6: 1.8 | G6: =D6/E6 -> 2083.3333 | H6: =G6*F6 -> 3750 | I6: =H6-D6 -> 2250 | J6: =I6/D6 -> 1.5 | K6: Light-Med Sweet Angola | L6: Bidding war 180p. Strategic buyer. | M6: ~£0
A7: A | B7: IMPP | C7: Imperial Petroleum | D7: 1500 | E7: 4.1 | F7: 20 | G7: =D7/E7 -> 365.85366 | H7: =G7*F7 -> 7317.0732 | I7: =H7-D7 -> 5817.0732 | J7: =I7/D7 -> 3.8780488 | K7: Shipping — Rate Driven | L7: Full squeeze $20+. Peak cycle. | M7: ~£0
A8: A | B8: GKP | C8: Gulf Keystone | D8: 1000 | E8: 2.04 | F8: 4.5 | G8: =D8/E8 -> 490.19608 | H8: =G8*F8 -> 2205.8824 | I8: =H8-D8 -> 1205.8824 | J8: =I8/D8 -> 1.2058824 | K8: Light Sweet CEYHAN PREM | L8: GKP $150 Brent. Ceyhan monopoly premium. | M8: ~£25
A9: A | B9: KOS | C9: Kosmos Energy | D9: 1000 | E9: 2.4 | F9: 10 | G9: =D9/E9 -> 416.66667 | H9: =G9*F9 -> 4166.6667 | I9: =H9-D9 -> 3166.6667 | J9: =I9/D9 -> 3.1666667 | K9: Premium Light Sweet + LNG | L9: KOS $10+. Every cargo at peak LNG. | M9: ~£0
A10: A | B10: FRO | C10: Frontline | D10: 500 | E10: 33.78 | F10: 70 | G10: =D10/E10 -> 14.801658 | H10: =G10*F10 -> 1036.116 | I10: =H10-D10 -> 536.11604 | J10: =I10/D10 -> 1.0722321 | K10: Shipping — 81 VLCCs | L10: VLCC $200k/day. Historic freight. | M10: ~£15
A11: B | B11: JSE | C11: Jadestone Energy | D11: 1000 | E11: 0.28 | F11: 0.75 | G11: =D11/E11 -> 3571.4286 | H11: =G11*F11 -> 2678.5714 | I11: =H11-D11 -> 1678.5714 | J11: =I11/D11 -> 1.6785714 | K11: Condensate ASIA PREMIUM | L11: Asia scrambles. Condensate $120+ equiv. | M11: ~£0
A12: B | B12: ENQ | C12: EnQuest | D12: 500 | E12: 0.13 | F12: 0.38 | G12: =D12/E12 -> 3846.1538 | H12: =G12*F12 -> 1461.5385 | I12: =H12-D12 -> 961.53846 | J12: =I12/D12 -> 1.9230769 | K12: Med Sour + ASIA PREMIUM | L12: Mega-merger. North Sea premium maxed. | M12: ~£4
A13: B | B13: RKH | C13: Rockhopper | D13: 500 | E13: 0.75 | F13: 1.8 | G13: =D13/E13 -> 666.66667 | H13: =G13*F13 -> 1200 | I13: =H13-D13 -> 700 | J13: =I13/D13 -> 1.4 | K13: Light Sweet Atlantic | L13: 1Bn bbl fully valued. | M13: ~£0
A14: C | B14: PXEN | C14: Prospex Energy | D14: 750 | E14: 0.0485 | F14: 0.25 | G14: =D14/E14 -> 15463.918 | H14: =G14*F14 -> 3865.9794 | I14: =H14-D14 -> 3115.9794 | J14: =I14/D14 -> 4.1546392 | K14: EU Gas — TTF Premium | L14: EU gas crisis 2.0. Strategic asset. | M14: ~£0
A15: C | B15: BOR | C15: Borders & Southern | D15: 750 | E15: 0.1 | F15: 1 | G15: =D15/E15 -> 7500 | H15: =G15*F15 -> 7500 | I15: =H15-D15 -> 6750 | J15: =I15/D15 -> 9 | K15: ULTRA-LIGHT CONDENSATE | L15: Partner + FID. Darwin fully valued. | M15: ~£0
A16: — | B16: CASH | C16: Reserve | D16: 1000 | H16: 1000 | I16: 0
B17: PORTFOLIO TOTAL | D17: =SUM(D6:D16) -> 10000 | H17: =SUM(H6:H16) -> 36181.828 | I17: =H17-D17 -> 26181.828 | J17: =I17/D17 -> 2.6181828
A19: ABSOLUTE CEILING — Oil $140-150. IMPP squeezes past NAV. BOR partner. PXEN full permits. Prolonged Hormuz. Historic energy crisis.
A20: Invested: | C20: =D17 -> 10000
A21: Value: | C21: =H17 -> 36181.828
A22: Profit: | C22: =I17 -> 26181.828
A23: Return: | C23: =J17 -> 2.6181828

Sheet SCENARIO COMPARISON
A1: DNA ENTERTAINMENT — ALL 6 SCENARIOS SIDE-BY-SIDE
A3: Scenario | B3: Oil Price | C3: Deployed | D3: Portfolio Value | E3: Total Profit | F3: Return % | G3: Probability | H3: Our Framework | I3: vs Gemini
A4: BEAR CASE | B4: $60-70 | C4: ='BEAR CASE'!D17 -> 10000 | D4: ='BEAR CASE'!H17 -> 7344.279 | E4: ='BEAR CASE'!I17 -> -2655.721 | F4: ='BEAR CASE'!J17 -> -0.2655721 | G4: ~35-40% | H4: £7,344 (-26.6%) | I4: ~£7,500 (-25%)
A5: BASE CASE | B5: $75-85 | C5: ='BASE CASE'!D17 -> 10000 | D5: ='BASE CASE'!H17 -> 14878.604 | E5: ='BASE CASE'!I17 -> 4878.6038 | F5: ='BASE CASE'!J17 -> 0.48786038 | G5: ~45-50% | H5: £14,879 (+48.8%) | I5: ~£14,000 (+40%)
A6: REALISTIC MOONSHOT | B6: $110-120 | C6: ='REALISTIC MOONSHOT'!D17 -> 10000 | D6: ='REALISTIC MOONSHOT'!H17 -> 16727.109 | E6: ='REALISTIC MOONSHOT'!I17 -> 6727.1089 | F6: ='REALISTIC MOONSHOT'!J17 -> 0.67271089 | G6: ~25-30% | H6: £16,727 (+67%) | I6: ~£15,000 (+50%)
A7: OPTIMISTIC MOONSHOT | B7: $120-130 | C7: ='OPTIMISTIC MOONSHOT'!D17 -> 10000 | D7: ='OPTIMISTIC MOONSHOT'!H17 -> 23186.781 | E7: ='OPTIMISTIC MOONSHOT'!I17 -> 13186.781 | F7: ='OPTIMISTIC MOONSHOT'!J17 -> 1.3186781 | G7: ~10-15% | H7: £23,187 (+132%) | I7: ~£20,000 (+100%)
A8: EVERYTHING HITS | B8: $130+ | C8: ='EVERYTHING HITS'!D17 -> 10000 | D8: ='EVERYTHING HITS'!H17 -> 30150.691 | E8: ='EVERYTHING HITS'!I17 -> 20150.691 | F8: ='EVERYTHING HITS'!J17 -> 2.0150691 | G8: ~5-8% | H8: £30,151 (+201%) | I8: ~£25,037 (+150%)
A9: ABSOLUTE CEILING | B9: $140-150 | C9: ='ABSOLUTE CEILING'!D17 -> 10000 | D9: ='ABSOLUTE CEILING'!H17 -> 36181.828 | E9: ='ABSOLUTE CEILING'!I17 -> 26181.828 | F9: ='ABSOLUTE CEILING'!J17 -> 2.6181828 | G9: ~2-5% | H9: £36,182 (+262%) | I9: ~£27,383 (+173%)
A12: WHY OUR FRAMEWORK OUTPERFORMS GEMINI'S BY £8,799 AT THE CEILING:
A13: → 7 of 10 positions have CONFIRMED catalysts (AET bid process, GKP restart, JSE Vietnam FDP, IMPP peak rates, FRO peak rates, KOS GTA cargoes, ENQ Magnus drilling)
A14: → 5 dedicated squeeze candidates (IMPP HIGH, AET/GKP/PXEN/BOR MED-HIGH) vs Gemini's 1 (IMPP only)
A15: → Crude quality engine: Johan Sverdrup +$11.30, Asian condensate +$10, Bonny Light +$5 — premiums NOT in Gemini's model
A16: → BOR + PXEN speculative tail: £1,500 deployed could return £4,000-11,000 if catalysts land — Gemini excluded these entirely
A18: GEMINI TACTICAL OVERLAY ADOPTED:
A19: → Tranche deployment (Apr 1-3) instead of lump sum
A20: → Hard stops on entry, convert to 15% trailing stops at +30%
A21: → Cyclone Narelle JSE monitoring before full deployment
A22: → BORR Drilling watchlisted for post-crisis entry (NOT bought now)
A24: EXIT STRATEGY: Systematic profit-taking by late June 2026. Ukraine precedent: ~4 months elevated before retracing.
A25: ⚠️ NOT FINANCIAL ADVICE. Speculative analysis only. All investments carry risk including total loss. Consult a qualified advisor.

Sheet CATALYST TIMELINE
A1: CATALYST TIMELINE — Week-by-Week Action Plan | March–June 2026
A3: When | B3: Ticker | C3: Event | D3: Bull Outcome | E3: Bear Outcome | F3: Prob | G3: Action Signal | H3: Monitor Via
A4: Apr 1 | B4: ALL | C4: TRANCHE 1 DEPLOYMENT — AET, IMPP, GKP, KOS, FRO | D4: Positions established at market open | E4: Miss the move if delayed | F4: 100% | G4: ✅ EXECUTE | H4: FreeTrade app
A5: Apr 1-3 | B5: JSE/ENQ/RKH | C5: TRANCHE 2 — After JSE Stag RNS update | D5: Full position if Stag damage minor | E5: Reduce JSE if major damage | F5: 90% | G5: ✅ EXECUTE | H5: Investegate RNS
A6: Apr 1-3 | B6: PXEN/BOR | C6: TRANCHE 2 SPEC — Establish base positions | D6: Speculative positions live | E6: Accept binary risk | F6: 100% | G6: ✅ EXECUTE | H6: FreeTrade app
A7: Apr 4 | B7: GKP | C7: AIM 100 quarterly rebalance | D7: GKP joins AIM 100 → institutional buying | E7: No index effect | F7: 50% | G7: 🟡 HOLD | H7: AIM announcements
A8: Apr 10 | B8: GKP | C8: Dividend record date ($12.5M interim) | D8: Capture 12.4% yield | E8: Already priced in | F8: 95% | G8: ✅ HOLD through | H8: Investegate RNS
A9: Apr 27 | B9: GKP | C9: Dividend payment date | D9: Cash in account | E9: — | F9: 95% | G9: ✅ COLLECT | H9: FreeTrade app
A10: Apr | B10: AXL | C10: Icaco exploration well spuds (IF added to FT) | D10: Discovery → AXL 25p+ | E10: Dry hole | F10: 70% | G10: 🟡 WATCH | H10: Investegate RNS
A11: Apr-May | B11: AET | C11: Rule 2.7 formal bid (Jefferies process) | D11: Bid 95-120p → take 50% profit | E11: No offer → 60p | F11: 65% | G11: 🎯 KEY — partial exit at bid | H11: Investegate RNS
A12: Apr-May | B12: GKP | C12: International pricing confirmation | D12: GKP 280-350p → deploy £300 cash | E12: Extended interim pricing | F12: 60% | G12: 🔴 DEPLOY CASH if confirmed | H12: Investegate RNS
A13: Q2 | B13: IMPP | C13: Q1 2026 earnings at peak Hormuz freight | D13: EPS explosion → $6-8+ re-rating | E13: Market ignores (dilution fear) | F13: 90% | G13: ✅ HOLD through earnings | H13: Seeking Alpha
A14: Q2 | B14: FRO | C14: Q1 earnings — VLCC $107k/day captured | D14: Analyst upgrades → FRO $40+ | E14: One-off quarter narrative | F14: 85% | G14: ✅ HOLD through earnings | H14: Seeking Alpha
... A23: IF | B23: ALL | C23: Hormuz extends past April | D23: Deploy £400 cash → IMPP (£200) + FRO (£200) | E23: — | F23: 55% | G23: 🔴 DEPLOY CASH | H23: Google Alerts

Sheet MONITORING SETUP
A1: CATALYST MONITORING — Free Tools Setup Guide
A3: Tool / Platform | B3: What to Monitor | C3: Tickers / Keywords | D3: Setup Action
A4: Investegate.co.uk | B4: UK RNS alerts (7AM drops). LEGALLY REQUIRED disclosures. | C4: AET, GKP, JSE, ENQ, RKH, PXEN, BOR | D4: Create free account → Add all 7 AIM/LSE tickers → Enable email alerts
A5: Seeking Alpha | B5: US stock news + earnings alerts | C5: IMPP, FRO, KOS | D5: Create free account → Add to portfolio → Enable 'News & Analysis' email alerts
A6: Google Alerts | B6: Macro / geopolitical triggers | C6: 'Strait of Hormuz shipping' 'VLCC rates' 'Iran ceasefire' | D6: Create 3 alerts → Set to 'As-it-happens' delivery → Email
A7: X (Twitter) List | B7: Real-time oil/shipping intelligence | C7: @TankerTrackers, @JavierBlas, @EnergyAspects | D7: Create private list → Turn on notifications for list
A8: FreeTrade App | B8: Price alerts for trailing stop triggers | C8: All 10 tickers at +30% entry | D8: Set price alerts in app for each Trail Trigger price
A9: TradingView (free) | B9: Technical chart alerts | C9: IMPP, FRO (for squeeze detection) | D9: Set alerts for volume spikes >3x average
A11: ⏱️ Daily routine: Check Investegate at 7:00 AM UK. Check Seeking Alpha pre-US open. Check Google Alerts throughout day. 15 minutes total.
