Workbook

Sheet MASTER ALLOCATION
A1: DNA ENTERTAINMENT — £10,000 FINAL DEPLOYMENT MODEL | 10 Positions + £1,000 Cash Reserve
A2: ⚠️ Speculative analysis. Not financial advice. All investments carry risk including total loss of capital. Consult a qualified financial advisor.
A4: Tier | B4: Ticker | C4: Company | D4: £ Alloc | E4: Entry Price | F4: Ccy | G4: Stop Loss | H4: Crude Quality | I4: API° | J4: Hormuz | K4: Squeeze Prob | L4: Catalyst 1 (Nearest) | M4: Prob | N4: Catalyst 2 | O4: Prob | P4: Key Risk | Q4: BEAR Mult | R4: BASE Mult | S4: BULL Mult | T4: Action
A5: A | B5: AET | C5: Afentra | D5: 1500 | E5: 0.72 | F5: £ | G5: 0.58 | H5: Light-Med Sweet Angola | I5: 28-32° | J5: V.STRONG | K5: MED-HIGH | L5: Rule 2.7 bid May-Jun (Jefferies) | M5: 0.65 | N5: Etu acquisition Q2 + Infill drilling | O5: 0.8 | P5: Bid may not materialise | Q5: 1.3 | R5: 2 | S5: 3 | T5: STRONG BUY
A6: A | B6: IMPP | C6: Imperial Petroleum | D6: 1500 | E6: 4.1 | F6: $ | G6: 2.8 | H6: Shipping - Rate Driven | I6: N/A | J6: EXTREME | K6: HIGH | L6: Q1 earnings at peak rates | M6: 0.9 | N6: Fleet 26 vessels + buyback | O6: 0.85 | P6: Dilutive offerings | Q6: 1.5 | R6: 2.5 | S6: 4 | T6: STRONG BUY
A7: A | B7: GKP | C7: Gulf Keystone | D7: 1000 | E7: 2.04 | F7: £ | G7: 1.65 | H7: Light Sweet CEYHAN | I7: ~35° | J7: EXTREME BINARY | K7: MED-HIGH | L7: RESTART CONFIRMED Mar 27 | M7: 0.95 | N7: Intl pricing + Div Apr 27 | O7: 0.6 | P7: Iran conflict proximity | Q7: 0.5 | R7: 1.8 | S7: 3.5 | T7: HOLD→BUY
A8: A | B8: FRO | C8: Frontline | D8: 500 | E8: 33.78 | F8: $ | G8: 25 | H8: Shipping - 81 VLCCs | I8: N/A | J8: EXTREME | K8: MED-HIGH | L8: Q1 earnings $107k/day VLCC | M8: 0.9 | N8: Newbuilding deliveries Q2 | O8: 0.8 | P8: Cyclical rate collapse | Q8: 0.8 | R8: 1.5 | S8: 2.5 | T8: BUY
A9: A | B9: KOS | C9: Kosmos Energy | D9: 1000 | E9: 2.4 | F9: $ | G9: 1.6 | H9: Premium Light Sweet + LNG | I9: ~37° | J9: V.STRONG | K9: MED-HIGH | L9: GTA LNG cargoes ramp NOW | M9: 0.85 | N9: Jubilee optimisation + analyst upgrades | O9: 0.7 | P9: Debt leverage | Q9: 1.3 | R9: 2.5 | S9: 3.5 | T9: BUY
A10: B | B10: JSE | C10: Jadestone Energy | D10: 1000 | E10: 0.28 | F10: £ | G10: 0.2 | H10: Condensate ASIA PREMIUM | I10: 38-47° | J10: STRONG | K10: MED-HIGH | L10: Vietnam FDP CONFIRMED Mar 18 | M10: 1 | N10: PM323 Malaysia drilling Q2 | O10: 0.7 | P10: Hedging caps upside | Q10: 1 | R10: 1.7 | S10: 2.5 | T10: STRONG BUY
A11: B | B11: ENQ | C11: EnQuest | D11: 500 | E11: 0.13 | F11: £ | G11: 0.09 | H11: Med Sour + ASIA PREMIUM | I11: 30-40° | J11: STRONG | K11: MED-HIGH | L11: Magnus 6-well infill Q2 | M11: 0.85 | N11: Seligi gas 100mmscf/d + Serica | O11: 0.6 | P11: UK windfall tax 78% | Q11: 1 | R11: 1.8 | S11: 2.5 | T11: BUY
A12: B | B12: RKH | C12: Rockhopper | D12: 500 | E12: 0.75 | F12: £ | G12: 0.55 | H12: Light Sweet Atlantic | I12: ~32° | J12: V.STRONG | K12: MED-HIGH | L12: Sea Lion Phase 1 engineering | M12: 0.85 | N12: Navitas milestones + FPSO | O12: 0.7 | P12: Argentina geo risk | Q12: 1 | R12: 1.5 | S12: 2.5 | T12: HOLD
A13: C | B13: PXEN | C13: Prospex Energy | D13: 750 | E13: 0.0485 | F13: £ | G13: 0.03 | H13: EU Gas TTF Premium | I13: Gas | J13: V.STRONG | K13: MED-HIGH | L13: El Romeral permits (EIA cleared) | M13: 0.58 | N13: Polish licences + TTF spike | O13: 0.5 | P13: Spanish permitting delays | Q13: 1.2 | R13: 2.5 | S13: 5 | T13: SPEC BUY
A14: C | B14: BOR | C14: Borders & Southern | D14: 750 | E14: 0.1 | F14: £ | G14: 0.05 | H14: ULTRA-LIGHT CONDENSATE | I14: 46-49° | J14: V.STRONG | K14: MED-HIGH | L14: Partner discussions (farm-out) | M14: 0.35 | N14: Licence deadline Dec 2026 | O14: 0.7 | P14: Cash runway / binary | Q14: 0.7 | R14: 2 | S14: 8 | T14: SPEC BUY
A15: — | B15: CASH | C15: Dry Powder Reserve | D15: 1000 | E15: — | H15: Deploy on confirmed catalysts (bid/partner/strait extension)
B16: TOTAL DEPLOYED | D16: =SUM(D5:D15) -> 10000
A18: CASH DEPLOYMENT RULES:
A19: → If AET bid confirmed: Deploy £300 into AET on formal offer announcement (ride the bid premium)
A20: → If GKP international pricing confirmed: Deploy £300 into GKP on pricing announcement
A21: → If Hormuz extends past April: Deploy £400 into IMPP + FRO (freight rates sustain longer)
A22: → If BOR partner announced: Deploy full remaining cash into BOR immediately (binary moonshot)

Sheet BEAR CASE
A1: DNA ENTERTAINMENT — BEAR CASE
A2: Ceasefire announced. Oil drops to $60-70. Squeeze conditions evaporate. Stop-losses protect capital.
A4: Ticker | B4: Company | C4: £ Invested | D4: Entry Price | E4: Target Price | F4: Shares (approx) | G4: £ Return | H4: Profit £ | I4: Return % | J4: Crude Quality Edge | K4: Probability Assessment | L4: Notes
A5: AET | B5: Afentra | C5: 1500 | D5: 0.72 | E5: 0.58 | F5: =C5/D5 -> 2083.3333 | G5: =F5*E5 -> 1208.3333 | H5: =G5-C5 -> -291.66667 | I5: =H5/C5 -> -0.19444444 | J5: Light-Med Sweet Angola | K5: 40% | L5: Stop-loss triggered at 58p. Bid process may still protect.
A6: IMPP | B6: Imperial Petroleum | C6: 1500 | D6: 4.1 | E6: 2.8 | F6: =C6/D6 -> 365.85366 | G6: =F6*E6 -> 1024.3902 | H6: =G6-C6 -> -475.60976 | I6: =H6/C6 -> -0.31707317 | J6: Shipping - Rate Driven | K6: 30% | L6: Stop-loss at $2.80. Fleet value provides floor.
A7: GKP | B7: Gulf Keystone | C7: 1000 | D7: 2.04 | E7: 1.65 | F7: =C7/D7 -> 490.19608 | G7: =F7*E7 -> 808.82353 | H7: =G7-C7 -> -191.17647 | I7: =H7/C7 -> -0.19117647 | J7: Light Sweet CEYHAN | K7: 45% | L7: Stop-loss at 165p. Conflict extends shut-in.
A8: FRO | B8: Frontline | C8: 500 | D8: 33.78 | E8: 25 | F8: =C8/D8 -> 14.801658 | G8: =F8*E8 -> 370.04144 | H8: =G8-C8 -> -129.95856 | I8: =H8/C8 -> -0.25991711 | J8: Shipping - 81 VLCCs | K8: 35% | L8: Stop-loss at $25. Rates collapse on ceasefire.
A9: KOS | B9: Kosmos Energy | C9: 1000 | D9: 2.4 | E9: 1.6 | F9: =C9/D9 -> 416.66667 | G9: =F9*E9 -> 666.66667 | H9: =G9-C9 -> -333.33333 | I9: =H9/C9 -> -0.33333333 | J9: Premium Light Sweet + LNG | K9: 35% | L9: Stop-loss at $1.60. Debt weighs.
A10: JSE | B10: Jadestone Energy | C10: 1000 | D10: 0.28 | E10: 0.2 | F10: =C10/D10 -> 3571.4286 | G10: =F10*E10 -> 714.28571 | H10: =G10-C10 -> -285.71429 | I10: =H10/C10 -> -0.28571429 | J10: Condensate ASIA PREMIUM | K10: 25% | L10: Stop-loss at 20p. FDP confirmed provides some floor.
A11: ENQ | B11: EnQuest | C11: 500 | D11: 0.13 | E11: 0.09 | F11: =C11/D11 -> 3846.1538 | G11: =F11*E11 -> 346.15385 | H11: =G11-C11 -> -153.84615 | I11: =H11/C11 -> -0.30769231 | J11: Med Sour + ASIA PREMIUM | K11: 40% | L11: Stop-loss at 9p. UK tax + low oil.
A12: RKH | B12: Rockhopper | C12: 500 | D12: 0.75 | E12: 0.55 | F12: =C12/D12 -> 666.66667 | G12: =F12*E12 -> 366.66667 | H12: =G12-C12 -> -133.33333 | I12: =H12/C12 -> -0.26666667 | J12: Light Sweet Atlantic | K12: 30% | L12: Stop-loss at 55p. Development delays.
A13: PXEN | B13: Prospex Energy | C13: 750 | D13: 0.0485 | E13: 0.03 | F13: =C13/D13 -> 15463.918 | G13: =F13*E13 -> 463.91753 | H13: =G13-C13 -> -286.08247 | I13: =H13/C13 -> -0.3814433 | J13: EU Gas TTF Premium | K13: 50% | L13: Stop-loss at 3p. Permits delayed.
A14: BOR | B14: Borders & Southern | C14: 750 | D14: 0.1 | E14: 0.05 | F14: =C14/D14 -> 7500 | G14: =F14*E14 -> 375 | H14: =G14-C14 -> -375 | I14: =H14/C14 -> -0.5 | J14: ULTRA-LIGHT CONDENSATE | K14: 60% | L14: Stop-loss at 5p. No partner found.
A15: CASH | B15: Dry Powder | C15: 1000 | G15: 1000 | H15: 0 | I15: 0
B16: PORTFOLIO TOTAL | C16: =SUM(C5:C15) -> 10000 | G16: =SUM(G5:G15) -> 7344.279 | H16: =G16-C16 -> -2655.721 | I16: =H16/C16 -> -0.2655721
A18: SCENARIO: BEAR CASE
A19: Ceasefire announced. Oil drops to $60-70. Squeeze conditions evaporate. Stop-losses protect capital.
A21: Total Invested: | C21: =C16 -> 10000
A22: Portfolio Value: | C22: =G16 -> 7344.279
A23: Total Profit: | C23: =H16 -> -2655.721
A24: Return %: | C24: =I16 -> -0.2655721

Sheet BASE CASE
A1: DNA ENTERTAINMENT — BASE CASE
A2: Hormuz resolves Q3. Oil settles $75-85. Most company catalysts still fire on fundamentals. ~89% return.
A4: Ticker | B4: Company | C4: £ Invested | D4: Entry Price | E4: Target Price | F4: Shares (approx) | G4: £ Return | H4: Profit £ | I4: Return % | J4: Crude Quality Edge | K4: Probability Assessment | L4: Notes
A5: AET | B5: Afentra | C5: 1500 | D5: 0.72 | E5: 0.85 | F5: =C5/D5 -> 2083.3333 | G5: =F5*E5 -> 1770.8333 | H5: =G5-C5 -> 270.83333 | I5: =H5/C5 -> 0.18055556 | J5: Light-Med Sweet Angola | K5: 50% | L5: Bid process completes at modest premium.
A6: IMPP | B6: Imperial Petroleum | C6: 1500 | D6: 4.1 | E6: 8 | F6: =C6/D6 -> 365.85366 | G6: =F6*E6 -> 2926.8293 | H6: =G6-C6 -> 1426.8293 | I6: =H6/C6 -> 0.95121951 | J6: Shipping - Rate Driven | K6: 45% | L6: Re-rates towards book. Fleet generating cash.
A7: GKP | B7: Gulf Keystone | C7: 1000 | D7: 2.04 | E7: 2.8 | F7: =C7/D7 -> 490.19608 | G7: =F7*E7 -> 1372.549 | H7: =G7-C7 -> 372.54902 | I7: =H7/C7 -> 0.37254902 | J7: Light Sweet CEYHAN | K7: 40% | L7: International pricing partially achieved.
A8: FRO | B8: Frontline | C8: 500 | D8: 33.78 | E8: 40 | F8: =C8/D8 -> 14.801658 | G8: =F8*E8 -> 592.06631 | H8: =G8-C8 -> 92.066311 | I8: =H8/C8 -> 0.18413262 | J8: Shipping - 81 VLCCs | K8: 40% | L8: Rates normalise but still profitable.
A9: KOS | B9: Kosmos Energy | C9: 1000 | D9: 2.4 | E9: 4.5 | F9: =C9/D9 -> 416.66667 | G9: =F9*E9 -> 1875 | H9: =G9-C9 -> 875 | I9: =H9/C9 -> 0.875 | J9: Premium Light Sweet + LNG | K9: 45% | L9: GTA LNG delivers. Moderate oil price.
A10: JSE | B10: Jadestone Energy | C10: 1000 | D10: 0.28 | E10: 0.4 | F10: =C10/D10 -> 3571.4286 | G10: =F10*E10 -> 1428.5714 | H10: =G10-C10 -> 428.57143 | I10: =H10/C10 -> 0.42857143 | J10: Condensate ASIA PREMIUM | K10: 50% | L10: FDP booked. PM323 wells deliver.
A11: ENQ | B11: EnQuest | C11: 500 | D11: 0.13 | E11: 0.18 | F11: =C11/D11 -> 3846.1538 | G11: =F11*E11 -> 692.30769 | H11: =G11-C11 -> 192.30769 | I11: =H11/C11 -> 0.38461538 | J11: Med Sour + ASIA PREMIUM | K11: 45% | L11: Magnus drilling adds production.
A12: RKH | B12: Rockhopper | C12: 500 | D12: 0.75 | E12: 0.95 | F12: =C12/D12 -> 666.66667 | G12: =F12*E12 -> 633.33333 | H12: =G12-C12 -> 133.33333 | I12: =H12/C12 -> 0.26666667 | J12: Light Sweet Atlantic | K12: 45% | L12: Development milestones met on schedule.
A13: PXEN | B13: Prospex Energy | C13: 750 | D13: 0.0485 | E13: 0.08 | F13: =C13/D13 -> 15463.918 | G13: =F13*E13 -> 1237.1134 | H13: =G13-C13 -> 487.1134 | I13: =H13/C13 -> 0.64948454 | J13: EU Gas TTF Premium | K13: 35% | L13: Permits progressing. Production from existing wells.
A14: BOR | B14: Borders & Southern | C14: 750 | D14: 0.1 | E14: 0.18 | F14: =C14/D14 -> 7500 | G14: =F14*E14 -> 1350 | H14: =G14-C14 -> 600 | I14: =H14/C14 -> 0.8 | J14: ULTRA-LIGHT CONDENSATE | K14: 25% | L14: Farm-out discussions continue. Licence safe.
A15: CASH | B15: Dry Powder | C15: 1000 | G15: 1000 | H15: 0 | I15: 0
B16: PORTFOLIO TOTAL | C16: =SUM(C5:C15) -> 10000 | G16: =SUM(G5:G15) -> 14878.604 | H16: =G16-C16 -> 4878.6038 | I16: =H16/C16 -> 0.48786038
A18: SCENARIO: BASE CASE
A19: Hormuz resolves Q3. Oil settles $75-85. Most company catalysts still fire on fundamentals. ~89% return.
A21: Total Invested: | C21: =C16 -> 10000
A22: Portfolio Value: | C22: =G16 -> 14878.604
A23: Total Profit: | C23: =H16 -> 4878.6038
A24: Return %: | C24: =I16 -> 0.48786038

Sheet REALISTIC MOONSHOT
A1: DNA ENTERTAINMENT — REALISTIC MOONSHOT
A2: Oil $110-120 sustained. Most catalysts fire. Moderate re-ratings. ~170% return.
A4: Ticker | B4: Company | C4: £ Invested | D4: Entry Price | E4: Target Price | F4: Shares (approx) | G4: £ Return | H4: Profit £ | I4: Return % | J4: Crude Quality Edge | K4: Probability Assessment | L4: Notes
A5: AET | B5: Afentra | C5: 1500 | D5: 0.72 | E5: 1 | F5: =C5/D5 -> 2083.3333 | G5: =F5*E5 -> 2083.3333 | H5: =G5-C5 -> 583.33333 | I5: =H5/C5 -> 0.38888889 | J5: Light-Med Sweet Angola | K5: 30% | L5: Bid at 100p in $110 oil environment.
A6: IMPP | B6: Imperial Petroleum | C6: 1500 | D6: 4.1 | E6: 8 | F6: =C6/D6 -> 365.85366 | G6: =F6*E6 -> 2926.8293 | H6: =G6-C6 -> 1426.8293 | I6: =H6/C6 -> 0.95121951 | J6: Shipping - Rate Driven | K6: 25% | L6: Fleet at 26 vessels. Q1 earnings explosive.
A7: GKP | B7: Gulf Keystone | C7: 1000 | D7: 2.04 | E7: 3 | F7: =C7/D7 -> 490.19608 | G7: =F7*E7 -> 1470.5882 | H7: =G7-C7 -> 470.58824 | I7: =H7/C7 -> 0.47058824 | J7: Light Sweet CEYHAN | K7: 25% | L7: Full restart + international pricing $90+.
A8: FRO | B8: Frontline | C8: 500 | D8: 33.78 | E8: 42 | F8: =C8/D8 -> 14.801658 | G8: =F8*E8 -> 621.66963 | H8: =G8-C8 -> 121.66963 | I8: =H8/C8 -> 0.24333925 | J8: Shipping - 81 VLCCs | K8: 25% | L8: VLCC rates sustained $100k+/day.
A9: KOS | B9: Kosmos Energy | C9: 1000 | D9: 2.4 | E9: 5 | F9: =C9/D9 -> 416.66667 | G9: =F9*E9 -> 2083.3333 | H9: =G9-C9 -> 1083.3333 | I9: =H9/C9 -> 1.0833333 | J9: Premium Light Sweet + LNG | K9: 30% | L9: GTA + Jubilee at $110 Brent. FCF inflection.
A10: JSE | B10: Jadestone Energy | C10: 1000 | D10: 0.28 | E10: 0.45 | F10: =C10/D10 -> 3571.4286 | G10: =F10*E10 -> 1607.1429 | H10: =G10-C10 -> 607.14286 | I10: =H10/C10 -> 0.60714286 | J10: Condensate ASIA PREMIUM | K10: 25% | L10: FDP + PM323 + condensate $10+ premium.
A11: ENQ | B11: EnQuest | C11: 500 | D11: 0.13 | E11: 0.22 | F11: =C11/D11 -> 3846.1538 | G11: =F11*E11 -> 846.15385 | H11: =G11-C11 -> 346.15385 | I11: =H11/C11 -> 0.69230769 | J11: Med Sour + ASIA PREMIUM | K11: 25% | L11: Magnus + Seligi + Sverdrup-type premium.
A12: RKH | B12: Rockhopper | C12: 500 | D12: 0.75 | E12: 1 | F12: =C12/D12 -> 666.66667 | G12: =F12*E12 -> 666.66667 | H12: =G12-C12 -> 166.66667 | I12: =H12/C12 -> 0.33333333 | J12: Light Sweet Atlantic | K12: 25% | L12: Sea Lion advancing. Oil at $110+.
A13: PXEN | B13: Prospex Energy | C13: 750 | D13: 0.0485 | E13: 0.1 | F13: =C13/D13 -> 15463.918 | G13: =F13*E13 -> 1546.3918 | H13: =G13-C13 -> 796.39175 | I13: =H13/C13 -> 1.0618557 | J13: EU Gas TTF Premium | K13: 20% | L13: Permits granted. 2 wells producing. TTF €50+.
A14: BOR | B14: Borders & Southern | C14: 750 | D14: 0.1 | E14: 0.25 | F14: =C14/D14 -> 7500 | G14: =F14*E14 -> 1875 | H14: =G14-C14 -> 1125 | I14: =H14/C14 -> 1.5 | J14: ULTRA-LIGHT CONDENSATE | K14: 15% | L14: Farm-out interest from Sea Lion de-risking.
A15: CASH | B15: Dry Powder | C15: 1000 | G15: 1000 | H15: 0 | I15: 0
B16: PORTFOLIO TOTAL | C16: =SUM(C5:C15) -> 10000 | G16: =SUM(G5:G15) -> 16727.109 | H16: =G16-C16 -> 6727.1089 | I16: =H16/C16 -> 0.67271089
A18: SCENARIO: REALISTIC MOONSHOT
A19: Oil $110-120 sustained. Most catalysts fire. Moderate re-ratings. ~170% return.
A21: Total Invested: | C21: =C16 -> 10000
A22: Portfolio Value: | C22: =G16 -> 16727.109
A23: Total Profit: | C23: =H16 -> 6727.1089
A24: Return %: | C24: =I16 -> 0.67271089

Sheet OPTIMISTIC MOONSHOT
A1: DNA ENTERTAINMENT — OPTIMISTIC MOONSHOT
A2: Oil $120-130 sustained. All catalysts fire. Strong re-ratings. ~250% return.
A4: Ticker | B4: Company | C4: £ Invested | D4: Entry Price | E4: Target Price | F4: Shares (approx) | G4: £ Return | H4: Profit £ | I4: Return % | J4: Crude Quality Edge | K4: Probability Assessment | L4: Notes
A5: AET | B5: Afentra | C5: 1500 | D5: 0.72 | E5: 1.2 | F5: =C5/D5 -> 2083.3333 | G5: =F5*E5 -> 2500 | H5: =G5-C5 -> 1000 | I5: =H5/C5 -> 0.66666667 | J5: Light-Med Sweet Angola | K5: 15% | L5: Competitive bid at 120p. Multiple bidders.
A6: IMPP | B6: Imperial Petroleum | C6: 1500 | D6: 4.1 | E6: 12 | F6: =C6/D6 -> 365.85366 | G6: =F6*E6 -> 4390.2439 | H6: =G6-C6 -> 2890.2439 | I6: =H6/C6 -> 1.9268293 | J6: Shipping - Rate Driven | K6: 15% | L6: NAV re-rating begins. Buyback reduces float.
A7: GKP | B7: Gulf Keystone | C7: 1000 | D7: 2.04 | E7: 3.6 | F7: =C7/D7 -> 490.19608 | G7: =F7*E7 -> 1764.7059 | H7: =G7-C7 -> 764.70588 | I7: =H7/C7 -> 0.76470588 | J7: Light Sweet CEYHAN | K7: 12% | L7: International pricing at $120+. Ceyhan premium.
A8: FRO | B8: Frontline | C8: 500 | D8: 33.78 | E8: 50 | F8: =C8/D8 -> 14.801658 | G8: =F8*E8 -> 740.08289 | H8: =G8-C8 -> 240.08289 | I8: =H8/C8 -> 0.48016578 | J8: Shipping - 81 VLCCs | K8: 15% | L8: VLCC $120k/day. Newbuildings online.
A9: KOS | B9: Kosmos Energy | C9: 1000 | D9: 2.4 | E9: 7 | F9: =C9/D9 -> 416.66667 | G9: =F9*E9 -> 2916.6667 | H9: =G9-C9 -> 1916.6667 | I9: =H9/C9 -> 1.9166667 | J9: Premium Light Sweet + LNG | K9: 15% | L9: GTA LNG at $25/MMBtu spot. KOS $7+.
A10: JSE | B10: Jadestone Energy | C10: 1000 | D10: 0.28 | E10: 0.54 | F10: =C10/D10 -> 3571.4286 | G10: =F10*E10 -> 1928.5714 | H10: =G10-C10 -> 928.57143 | I10: =H10/C10 -> 0.92857143 | J10: Condensate ASIA PREMIUM | K10: 12% | L10: All catalysts + 47° condensate at $15 prem.
A11: ENQ | B11: EnQuest | C11: 500 | D11: 0.13 | E11: 0.28 | F11: =C11/D11 -> 3846.1538 | G11: =F11*E11 -> 1076.9231 | H11: =G11-C11 -> 576.92308 | I11: =H11/C11 -> 1.1538462 | J11: Med Sour + ASIA PREMIUM | K11: 12% | L11: Magnus peak + Serica merger re-rating.
A12: RKH | B12: Rockhopper | C12: 500 | D12: 0.75 | E12: 1.2 | F12: =C12/D12 -> 666.66667 | G12: =F12*E12 -> 800 | H12: =G12-C12 -> 300 | I12: =H12/C12 -> 0.6 | J12: Light Sweet Atlantic | K12: 12% | L12: Sea Lion progress + Falklands premium.
A13: PXEN | B13: Prospex Energy | C13: 750 | D13: 0.0485 | E13: 0.15 | F13: =C13/D13 -> 15463.918 | G13: =F13*E13 -> 2319.5876 | H13: =G13-C13 -> 1569.5876 | I13: =H13/C13 -> 2.0927835 | J13: EU Gas TTF Premium | K13: 10% | L13: Full permits + 5 wells drilling. TTF €55+.
A14: BOR | B14: Borders & Southern | C14: 750 | D14: 0.1 | E14: 0.5 | F14: =C14/D14 -> 7500 | G14: =F14*E14 -> 3750 | H14: =G14-C14 -> 3000 | I14: =H14/C14 -> 4 | J14: ULTRA-LIGHT CONDENSATE | K14: 8% | L14: Partner identified. Term sheet signed.
A15: CASH | B15: Dry Powder | C15: 1000 | G15: 1000 | H15: 0 | I15: 0
B16: PORTFOLIO TOTAL | C16: =SUM(C5:C15) -> 10000 | G16: =SUM(G5:G15) -> 23186.781 | H16: =G16-C16 -> 13186.781 | I16: =H16/C16 -> 1.3186781
A18: SCENARIO: OPTIMISTIC MOONSHOT
A19: Oil $120-130 sustained. All catalysts fire. Strong re-ratings. ~250% return.
A21: Total Invested: | C21: =C16 -> 10000
A22: Portfolio Value: | C22: =G16 -> 23186.781
A23: Total Profit: | C23: =H16 -> 13186.781
A24: Return %: | C24: =I16 -> 1.3186781

Sheet EVERYTHING HITS
A1: DNA ENTERTAINMENT — EVERYTHING HITS
A2: Oil $130+ sustained. Squeezes materialise. Premium crude differentials widen. ~350% return.
A4: Ticker | B4: Company | C4: £ Invested | D4: Entry Price | E4: Target Price | F4: Shares (approx) | G4: £ Return | H4: Profit £ | I4: Return % | J4: Crude Quality Edge | K4: Probability Assessment | L4: Notes
A5: AET | B5: Afentra | C5: 1500 | D5: 0.72 | E5: 1.5 | F5: =C5/D5 -> 2083.3333 | G5: =F5*E5 -> 3125 | H5: =G5-C5 -> 1625 | I5: =H5/C5 -> 1.0833333 | J5: Light-Med Sweet Angola | K5: 8% | L5: Premium bid 150p. Oil $130+. Takeover war.
A6: IMPP | B6: Imperial Petroleum | C6: 1500 | D6: 4.1 | E6: 16 | F6: =C6/D6 -> 365.85366 | G6: =F6*E6 -> 5853.6585 | H6: =G6-C6 -> 4353.6585 | I6: =H6/C6 -> 2.902439 | J6: Shipping - Rate Driven | K6: 8% | L6: Squeeze towards NAV $11.38. Peak freight.
A7: GKP | B7: Gulf Keystone | C7: 1000 | D7: 2.04 | E7: 4.2 | F7: =C7/D7 -> 490.19608 | G7: =F7*E7 -> 2058.8235 | H7: =G7-C7 -> 1058.8235 | I7: =H7/C7 -> 1.0588235 | J7: Light Sweet CEYHAN | K7: 6% | L7: Intl pricing $130 Brent. Ceyhan only Med route.
A8: FRO | B8: Frontline | C8: 500 | D8: 33.78 | E8: 60 | F8: =C8/D8 -> 14.801658 | G8: =F8*E8 -> 888.09947 | H8: =G8-C8 -> 388.09947 | I8: =H8/C8 -> 0.77619893 | J8: Shipping - 81 VLCCs | K8: 8% | L8: VLCC $150k/day sustained. $2+/share divs.
A9: KOS | B9: Kosmos Energy | C9: 1000 | D9: 2.4 | E9: 8.5 | F9: =C9/D9 -> 416.66667 | G9: =F9*E9 -> 3541.6667 | H9: =G9-C9 -> 2541.6667 | I9: =H9/C9 -> 2.5416667 | J9: Premium Light Sweet + LNG | K9: 8% | L9: DCF $6.87 achieved. GTA + Jubilee dual peak.
A10: JSE | B10: Jadestone Energy | C10: 1000 | D10: 0.28 | E10: 0.65 | F10: =C10/D10 -> 3571.4286 | G10: =F10*E10 -> 2321.4286 | H10: =G10-C10 -> 1321.4286 | I10: =H10/C10 -> 1.3214286 | J10: Condensate ASIA PREMIUM | K10: 6% | L10: Condensate $15+ prem. Vietnam + Malaysia.
A11: ENQ | B11: EnQuest | C11: 500 | D11: 0.13 | E11: 0.33 | F11: =C11/D11 -> 3846.1538 | G11: =F11*E11 -> 1269.2308 | H11: =G11-C11 -> 769.23077 | I11: =H11/C11 -> 1.5384615 | J11: Med Sour + ASIA PREMIUM | K11: 6% | L11: Combined entity re-rates. Peak Sverdrup prem.
A12: RKH | B12: Rockhopper | C12: 500 | D12: 0.75 | E12: 1.5 | F12: =C12/D12 -> 666.66667 | G12: =F12*E12 -> 1000 | H12: =G12-C12 -> 500 | I12: =H12/C12 -> 1 | J12: Light Sweet Atlantic | K12: 6% | L12: Falklands premium. First oil fast-tracked.
A13: PXEN | B13: Prospex Energy | C13: 750 | D13: 0.0485 | E13: 0.2 | F13: =C13/D13 -> 15463.918 | G13: =F13*E13 -> 3092.7835 | H13: =G13-C13 -> 2342.7835 | I13: =H13/C13 -> 3.1237113 | J13: EU Gas TTF Premium | K13: 5% | L13: 5 wells + Selva + Viura + Poland. TTF €60+.
A14: BOR | B14: Borders & Southern | C14: 750 | D14: 0.1 | E14: 0.8 | F14: =C14/D14 -> 7500 | G14: =F14*E14 -> 6000 | H14: =G14-C14 -> 5250 | I14: =H14/C14 -> 7 | J14: ULTRA-LIGHT CONDENSATE | K14: 4% | L14: Partner announced. Farm-in terms agreed.
A15: CASH | B15: Dry Powder | C15: 1000 | G15: 1000 | H15: 0 | I15: 0
B16: PORTFOLIO TOTAL | C16: =SUM(C5:C15) -> 10000 | G16: =SUM(G5:G15) -> 30150.691 | H16: =G16-C16 -> 20150.691 | I16: =H16/C16 -> 2.0150691
A18: SCENARIO: EVERYTHING HITS
A19: Oil $130+ sustained. Squeezes materialise. Premium crude differentials widen. ~350% return.
A21: Total Invested: | C21: =C16 -> 10000
A22: Portfolio Value: | C22: =G16 -> 30150.691
A23: Total Profit: | C23: =H16 -> 20150.691
A24: Return %: | C24: =I16 -> 2.0150691

Sheet ABSOLUTE CEILING
A1: DNA ENTERTAINMENT — ABSOLUTE CEILING
A2: Oil $140-150. IMPP squeezes to NAV+. BOR partner. PXEN full permits. Prolonged Hormuz closure. ~450%+ return.
A4: Ticker | B4: Company | C4: £ Invested | D4: Entry Price | E4: Target Price | F4: Shares (approx) | G4: £ Return | H4: Profit £ | I4: Return % | J4: Crude Quality Edge | K4: Probability Assessment | L4: Notes
A5: AET | B5: Afentra | C5: 1500 | D5: 0.72 | E5: 1.8 | F5: =C5/D5 -> 2083.3333 | G5: =F5*E5 -> 3750 | H5: =G5-C5 -> 2250 | I5: =H5/C5 -> 1.5 | J5: Light-Med Sweet Angola | K5: 3% | L5: Bidding war 180p. Strategic buyer at peak oil.
A6: IMPP | B6: Imperial Petroleum | C6: 1500 | D6: 4.1 | E6: 20 | F6: =C6/D6 -> 365.85366 | G6: =F6*E6 -> 7317.0732 | H6: =G6-C6 -> 5817.0732 | I6: =H6/C6 -> 3.8780488 | J6: Shipping - Rate Driven | K6: 5% | L6: Full NAV squeeze $20. Peak cycle earnings.
A7: GKP | B7: Gulf Keystone | C7: 1000 | D7: 2.04 | E7: 4.5 | F7: =C7/D7 -> 490.19608 | G7: =F7*E7 -> 2205.8824 | H7: =G7-C7 -> 1205.8824 | I7: =H7/C7 -> 1.2058824 | J7: Light Sweet CEYHAN | K7: 3% | L7: GKP at $150 Brent + Ceyhan monopoly premium.
A8: FRO | B8: Frontline | C8: 500 | D8: 33.78 | E8: 70 | F8: =C8/D8 -> 14.801658 | G8: =F8*E8 -> 1036.116 | H8: =G8-C8 -> 536.11604 | I8: =H8/C8 -> 1.0722321 | J8: Shipping - 81 VLCCs | K8: 4% | L8: VLCC $200k/day. Historic freight peak.
A9: KOS | B9: Kosmos Energy | C9: 1000 | D9: 2.4 | E9: 10 | F9: =C9/D9 -> 416.66667 | G9: =F9*E9 -> 4166.6667 | H9: =G9-C9 -> 3166.6667 | I9: =H9/C9 -> 3.1666667 | J9: Premium Light Sweet + LNG | K9: 4% | L9: KOS $10+. GTA sells every cargo at peak LNG.
A10: JSE | B10: Jadestone Energy | C10: 1000 | D10: 0.28 | E10: 0.75 | F10: =C10/D10 -> 3571.4286 | G10: =F10*E10 -> 2678.5714 | H10: =G10-C10 -> 1678.5714 | I10: =H10/C10 -> 1.6785714 | J10: Condensate ASIA PREMIUM | K10: 3% | L10: Asia scrambles. Condensate = $120+ equiv.
A11: ENQ | B11: EnQuest | C11: 500 | D11: 0.13 | E11: 0.38 | F11: =C11/D11 -> 3846.1538 | G11: =F11*E11 -> 1461.5385 | H11: =G11-C11 -> 961.53846 | I11: =H11/C11 -> 1.9230769 | J11: Med Sour + ASIA PREMIUM | K11: 3% | L11: Mega-merger. North Sea premium maxed.
A12: RKH | B12: Rockhopper | C12: 500 | D12: 0.75 | E12: 1.8 | F12: =C12/D12 -> 666.66667 | G12: =F12*E12 -> 1200 | H12: =G12-C12 -> 700 | I12: =H12/C12 -> 1.4 | J12: Light Sweet Atlantic | K12: 3% | L12: Falklands = new frontier. 1Bn bbl valued.
A13: PXEN | B13: Prospex Energy | C13: 750 | D13: 0.0485 | E13: 0.25 | F13: =C13/D13 -> 15463.918 | G13: =F13*E13 -> 3865.9794 | H13: =G13-C13 -> 3115.9794 | I13: =H13/C13 -> 4.1546392 | J13: EU Gas TTF Premium | K13: 2% | L13: EU gas crisis 2.0. PXEN = strategic asset.
A14: BOR | B14: Borders & Southern | C14: 750 | D14: 0.1 | E14: 1 | F14: =C14/D14 -> 7500 | G14: =F14*E14 -> 7500 | H14: =G14-C14 -> 6750 | I14: =H14/C14 -> 9 | J14: ULTRA-LIGHT CONDENSATE | K14: 2% | L14: Partner + FID. Darwin fully valued.
A15: CASH | B15: Dry Powder | C15: 1000 | G15: 1000 | H15: 0 | I15: 0
B16: PORTFOLIO TOTAL | C16: =SUM(C5:C15) -> 10000 | G16: =SUM(G5:G15) -> 36181.828 | H16: =G16-C16 -> 26181.828 | I16: =H16/C16 -> 2.6181828
A18: SCENARIO: ABSOLUTE CEILING
A19: Oil $140-150. IMPP squeezes to NAV+. BOR partner. PXEN full permits. Prolonged Hormuz closure. ~450%+ return.
A21: Total Invested: | C21: =C16 -> 10000
A22: Portfolio Value: | C22: =G16 -> 36181.828
A23: Total Profit: | C23: =H16 -> 26181.828
A24: Return %: | C24: =I16 -> 2.6181828

Sheet SCENARIO COMPARISON
A1: DNA ENTERTAINMENT — ALL SCENARIOS SIDE-BY-SIDE
A3: Scenario | B3: Oil Price | C3: Deployed | D3: Portfolio Value | E3: Total Profit | F3: Return % | G3: Probability | H3: Risk Level
A4: BEAR CASE | B4: $60-70 | C4: =SUM('BEAR CASE'!C5:C15) -> 10000 | D4: ='BEAR CASE'!G16 -> 7344.279 | E4: ='BEAR CASE'!H16 -> -2655.721 | F4: ='BEAR CASE'!I16 -> -0.2655721 | G4: ~35-40% | H4: CAPITAL LOSS
A5: BASE CASE | B5: $75-85 | C5: =SUM('BASE CASE'!C5:C15) -> 10000 | D5: ='BASE CASE'!G16 -> 14878.604 | E5: ='BASE CASE'!H16 -> 4878.6038 | F5: ='BASE CASE'!I16 -> 0.48786038 | G5: ~45-50% | H5: MODERATE
A6: REALISTIC MOONSHOT | B6: $110-120 | C6: =SUM('REALISTIC MOONSHOT'!C5:C15) -> 10000 | D6: ='REALISTIC MOONSHOT'!G16 -> 16727.109 | E6: ='REALISTIC MOONSHOT'!H16 -> 6727.1089 | F6: ='REALISTIC MOONSHOT'!I16 -> 0.67271089 | G6: ~25-30% | H6: ELEVATED
A7: OPTIMISTIC MOONSHOT | B7: $120-130 | C7: =SUM('OPTIMISTIC MOONSHOT'!C5:C15) -> 10000 | D7: ='OPTIMISTIC MOONSHOT'!G16 -> 23186.781 | E7: ='OPTIMISTIC MOONSHOT'!H16 -> 13186.781 | F7: ='OPTIMISTIC MOONSHOT'!I16 -> 1.3186781 | G7: ~10-15% | H7: HIGH
A8: EVERYTHING HITS | B8: $130+ | C8: =SUM('EVERYTHING HITS'!C5:C15) -> 10000 | D8: ='EVERYTHING HITS'!G16 -> 30150.691 | E8: ='EVERYTHING HITS'!H16 -> 20150.691 | F8: ='EVERYTHING HITS'!I16 -> 2.0150691 | G8: ~5-8% | H8: VERY HIGH
A9: ABSOLUTE CEILING | B9: $140-150 | C9: =SUM('ABSOLUTE CEILING'!C5:C15) -> 10000 | D9: ='ABSOLUTE CEILING'!G16 -> 36181.828 | E9: ='ABSOLUTE CEILING'!H16 -> 26181.828 | F9: ='ABSOLUTE CEILING'!I16 -> 2.6181828 | G9: ~2-5% | H9: EXTREME
A11: ⚠️ DISCLAIMER: Theoretical scenarios only. Not financial advice. Past performance is not indicative of future results.
A13: KEY INSIGHT: 7 of 10 stocks have CONFIRMED catalysts (AET bid process, GKP restart, JSE Vietnam FDP, IMPP peak rates, FRO peak rates, KOS GTA cargoes, ENQ Magnus drilling)
A14: EXIT STRATEGY: Systematic profit-taking by late June 2026. Trail stops once conservative targets hit. Ukraine precedent: ~4 months elevated before retracing.
